.gitignore
LICENSE
MANIFEST.in
README.md
setup.py
swagger_descriptor/__init__.py
swagger_descriptor/json_schema.py
swagger_descriptor/swagger.py
swagger_descriptor.egg-info/PKG-INFO
swagger_descriptor.egg-info/SOURCES.txt
swagger_descriptor.egg-info/dependency_links.txt
swagger_descriptor.egg-info/top_level.txt